{
 "_id": "WduSXudt53GBHofAF",
 "url": "/%2F47.jpg",
 "socName": "Cityscapes",
 "objects": [
  {
   "classIndex": 6,
   "layer": 0,
   "polygon": [
    {
     "x": 335.25109148136863,
     "y": 486.873929671371
    },
    {
     "x": 352.57941584594033,
     "y": 471.2784377432565
    },
    {
     "x": 406.29722137611265,
     "y": 476.47693505262794
    },
    {
     "x": 427.09121061359866,
     "y": 497.270924290114
    },
    {
     "x": 394.16739432091236,
     "y": 512.8664162182286
    },
    {
     "x": 343.9152536636545,
     "y": 512.8664162182286
    }
   ],
   "label": "Brown"
  },
  {
   "classIndex": 6,
   "layer": 0,
   "polygon": [
    {
     "x": 576.1148001489153,
     "y": 492.07242698074253
    },
    {
     "x": 619.4356110603445,
     "y": 466.079940433885
    },
    {
     "x": 713.0085626290316,
     "y": 483.4082647984567
    },
    {
     "x": 673.1534165905168,
     "y": 502.46942159948554
    },
    {
     "x": 667.9549192811453,
     "y": 502.46942159948554
    },
    {
     "x": 622.9012759332588,
     "y": 509.40075134531423
    }
   ],
   "label": "Brown"
  }
 ],
 "tags": [],
 "folder": "",
 "file": "47.jpg",
 "lastEditDate": "2020-08-06T03:20:40.910Z",
 "firstEditDate": "2020-08-06T03:20:40.910Z"
}